LICENSE.txt
README.md
README.rst
setup.py
scripts/peerless_client
scripts/peerless_manager
src/eut/__init__.py
src/eut/abba/__init__.py
src/eut/abba/processor/__init__.py
src/eut/abba/processor/priority.py
src/eut/abba/processor/statuses.py
src/eut/peerless/__init__.py
src/eut/peerless/model.py
src/eut/peerless/solver.py
src/peerless.egg-info/PKG-INFO
src/peerless.egg-info/SOURCES.txt
src/peerless.egg-info/dependency_links.txt
src/peerless.egg-info/top_level.txt