Metadata-Version: 2.1
Name: peerless
Version: 1.0.3
Summary: Peerless Optimizer
Home-page: http://www.eveutils.com/peerless
Author: Eve Utils S.L.
Author-email: support@eveutils.com
License: EUPL-1.2
Keywords: mathematical optimization operations research numerical analysis
Platform: UNKNOWN
Classifier: Development Status :: 5 - Production/Stable
Classifier: Environment :: Console
Classifier: Intended Audience :: Developers
Classifier: Intended Audience :: Science/Research
Classifier: License :: OSI Approved :: European Union Public Licence 1.2 (EUPL 1.2)
Classifier: Natural Language :: English
Classifier: Operating System :: OS Independent
Classifier: Programming Language :: Python :: 3
Classifier: Programming Language :: Python :: 3 :: Only
Classifier: Topic :: Scientific/Engineering :: Mathematics
Classifier: Topic :: Software Development :: Libraries
Requires-Python: >=3.8
